loremipsumpy.py
loremipsumpy-0.0.2.dist-info/LICENSE.txt
loremipsumpy-0.0.2.dist-info/METADATA
loremipsumpy-0.0.2.dist-info/WHEEL
loremipsumpy-0.0.2.dist-info/top_level.txt
loremipsumpy-0.0.2.dist-info/RECORD
