Metadata-Version: 2.1
Name: loremipsumpy
Version: 0.0.2
Summary: This module generates lorem ipsum placeholder Text
Home-page: https://github.com/Ammyy9908/loremipsumpy
Author: Sumit
Author-email: sb78639@gmai.com
License: GNU General Public License v2 or later (GPLv2+)
Platform: UNKNOWN
Classifier: Programming Language :: Python :: 3
Classifier: Programming Language :: Python :: 3.6
Classifier: Programming Language :: Python :: 3.7
Classifier: Programming Language :: Python :: 3.8
Classifier: License :: OSI Approved :: GNU General Public License v2 or later (GPLv2+)
Classifier: Operating System :: OS Independent
Provides-Extra: dev
Requires-Dist: pytest (>=3.7) ; extra == 'dev'
